RTSAI/__init__.py
RTSAI/config.py
RTSAI/main.py
RTSAI/temp/kg_QALD_9/QALD9_construct.py
RTSAI/temp/kg_countries/countries.py
package_RTSAI-0.1.1.dist-info/METADATA
package_RTSAI-0.1.1.dist-info/WHEEL
package_RTSAI-0.1.1.dist-info/entry_points.txt
package_RTSAI-0.1.1.dist-info/top_level.txt
package_RTSAI-0.1.1.dist-info/RECORD
