Metadata-Version: 2.1
Name: package-RTSAI
Version: 0.1.1
Summary: The recreated RTSAI package with pip install. 
Home-page: https://github.com/WuKunhuan/RTSAI
Author: wukunhuan
Author-email: u3577163@connect.hku.hk
Project-URL: Source, https://github.com/WuKunhuan/RTSAI
Requires-Python: >=3.10.0
Requires-Dist: kgtk-wukunhuan
Requires-Dist: appdirs
Requires-Dist: pyautogui
Requires-Dist: pillow
Requires-Dist: pytest-shutil
